robustocs/__init__.py
robustocs/loaders.py
robustocs/pedigree.py
robustocs/solvers.py
robustocs/utils.py
robustocs-0.2.1.dist-info/METADATA
robustocs-0.2.1.dist-info/WHEEL
robustocs-0.2.1.dist-info/licenses/LICENSE
robustocs-0.2.1.dist-info/RECORD
