Metadata-Version: 2.3
Name: robustocs
Version: 0.2.1
Summary: Tools for solving robust optimal contribution selection problems
Project-URL: Homepage, https://github.com/Foggalong/RobustOCS
Project-URL: Documentation, https://github.com/Foggalong/RobustOCS/wiki
Project-URL: Issues, https://github.com/Foggalong/RobustOCS/issues
Author-email: Josh Fogg <j.fogg@ed.ac.uk>
License-File: LICENSE
Classifier: Development Status :: 4 - Beta
Classifier: License :: OSI Approved :: MIT License
Classifier: Operating System :: OS Independent
Classifier: Programming Language :: Python :: 3
Requires-Python: >=3.10
Requires-Dist: gurobipy>=11.0.3
Requires-Dist: highspy>=1.7.2
Requires-Dist: numpy>=1.21
Requires-Dist: scipy>=1.8.0
